ELA/Image_ela.py
ELA/__init__.py
metavision/Image_ela.py
metavision/__init__.py
metavision-0.0.3.dist-info/METADATA
metavision-0.0.3.dist-info/WHEEL
metavision-0.0.3.dist-info/top_level.txt
metavision-0.0.3.dist-info/RECORD
