Metadata-Version: 2.1
Name: metavision
Version: 0.0.3
Summary: Basic ELA package
Author: Abhishek Kumar
Author-email: <ykeep21@gmail.com>
Keywords: python,image,error level,compression,JPEG,residuals
Classifier: Development Status :: 1 - Planning
Classifier: Intended Audience :: Developers
Classifier: Programming Language :: Python :: 3
Classifier: Operating System :: Unix
Classifier: Operating System :: MacOS :: MacOS X
Classifier: Operating System :: Microsoft :: Windows
Requires-Dist: numpy
